plotassist/__init__.py
plotassist/matdata.py
plotassist/plotting.py
plotassist-0.6.dist-info/LICENSE
plotassist-0.6.dist-info/METADATA
plotassist-0.6.dist-info/WHEEL
plotassist-0.6.dist-info/top_level.txt
plotassist-0.6.dist-info/RECORD
