Metadata-Version: 2.1
Name: plotassist
Version: 0.6
Summary: A package for handling MATLAB data and working with Matplotlib plots
Home-page: https://github.com/CalvinSprouse/plotassist
Author: Calvin Sprouse
Author-email: calvinsprouse@proton.me
Classifier: Programming Language :: Python :: 3
Classifier: License :: OSI Approved :: MIT License
Classifier: Operating System :: OS Independent
Requires-Python: >=3.10
License-File: LICENSE
Requires-Dist: numpy
Requires-Dist: scipy
Requires-Dist: matplotlib
Requires-Dist: pandas
Requires-Dist: h5py
